artur_tancredo_alvarenga_puc_csv_converter/__init__.py
artur_tancredo_alvarenga_puc_csv_converter/converter.py
artur_tancredo_alvarenga_puc_csv_converter-1.1.1.dist-info/entry_points.txt
artur_tancredo_alvarenga_puc_csv_converter-1.1.1.dist-info/WHEEL
artur_tancredo_alvarenga_puc_csv_converter-1.1.1.dist-info/METADATA
artur_tancredo_alvarenga_puc_csv_converter-1.1.1.dist-info/RECORD
