Metadata-Version: 2.1
Name: artur-tancredo-alvarenga-puc-csv-converter
Version: 1.1.1
Summary: Trabalho da PUC - converter arquivo(s) de csv para json e json para csv
Author: Artur Tancredo de Alvarenga
Author-email: arturalvarenga@hotmail.com
Requires-Python: >=3.8.10,<4.0.0
Classifier: Programming Language :: Python :: 3
Classifier: Programming Language :: Python :: 3.10
Classifier: Programming Language :: Python :: 3.9
Requires-Dist: click (>=8.0.3,<9.0.0)
Requires-Dist: pandas (>=1.3.4,<2.0.0)
